{
 "allow_comments": 0,
 "allow_delete": 0,
 "allow_edit": 0,
 "allow_incomplete": 0,
 "allow_multiple": 0,
 "allow_print": 0,
 "anonymous": 0,
 "apply_document_permissions": 0,
 "button_label": "Save",
 "condition_json": "[]",
 "creation": "2024-10-16 10:51:37.986562",
 "doc_type": "Laporan",
 "docstatus": 0,
 "doctype": "Web Form",
 "idx": 0,
 "is_standard": 1,
 "list_columns": [],
 "login_required": 0,
 "max_attachment_size": 0,
 "modified": "2024-10-16 10:51:42.852294",
 "modified_by": "Administrator",
 "module": "Hr Management",
 "name": "laporan-anonymos",
 "owner": "Administrator",
 "published": 1,
 "route": "laporan-anonymos",
 "show_attachments": 0,
 "show_list": 0,
 "show_sidebar": 0,
 "title": "Laporan Anonymos",
 "web_form_fields": [
  {
   "allow_read_on_all_link_options": 0,
   "description": "Boleh di kosongkan",
   "fieldname": "nama",
   "fieldtype": "Data",
   "hidden": 0,
   "label": "Nama",
   "max_length": 0,
   "max_value": 0,
   "precision": "",
   "read_only": 0,
   "reqd": 0,
   "show_in_filter": 0
  },
  {
   "allow_read_on_all_link_options": 0,
   "fieldname": "jenis_laporan",
   "fieldtype": "Select",
   "hidden": 0,
   "label": "Jenis Laporan",
   "max_length": 0,
   "max_value": 0,
   "options": "Pengaduan\nLaporan\nLainnya",
   "precision": "",
   "read_only": 0,
   "reqd": 0,
   "show_in_filter": 0
  },
  {
   "allow_read_on_all_link_options": 0,
   "fieldname": "judul_laporan",
   "fieldtype": "Data",
   "hidden": 0,
   "label": "Judul Laporan",
   "max_length": 0,
   "max_value": 0,
   "precision": "",
   "read_only": 0,
   "reqd": 1,
   "show_in_filter": 0
  },
  {
   "allow_read_on_all_link_options": 0,
   "fieldname": "laporanpengaduan",
   "fieldtype": "Text",
   "hidden": 0,
   "label": "Laporan/Pengaduan",
   "max_length": 0,
   "max_value": 0,
   "precision": "",
   "read_only": 0,
   "reqd": 0,
   "show_in_filter": 0
  },
  {
   "allow_read_on_all_link_options": 0,
   "fieldname": "kritik_dan_saran",
   "fieldtype": "Text",
   "hidden": 0,
   "label": "Kritik dan Saran",
   "max_length": 0,
   "max_value": 0,
   "precision": "",
   "read_only": 0,
   "reqd": 0,
   "show_in_filter": 0
  }
 ]
}